LICENSE.TXT
setup.py
AlasbahiCul.egg-info/PKG-INFO
AlasbahiCul.egg-info/SOURCES.txt
AlasbahiCul.egg-info/dependency_links.txt
AlasbahiCul.egg-info/top_level.txt
code/__init__.py