Metadata-Version: 2.1
Name: AlasbahiCul
Version: 0.1
Summary: Sample fuad lib in python
Home-page: UNKNOWN
Author: Fuad Alasbahi
License: UNKNOWN
Platform: UNKNOWN
License-File: LICENSE.TXT
